Workbook

Sheet Sheet1
A1: FinInsight Analytics Pvt. Ltd.
A2: Date | B2: Department | C2: Revenue (Rs.) | D2: Expenses (Rs.) | E2: Profit (Rs.)
A3: 45962 | B3: Sales | C3: 240000 | D3: 160000 | E3: =C3-D3 -> 80000
A4: 45963 | B4: Marketing | C4: 150000 | D4: 105000 | E4: =C4-D4 -> 45000
A5: 45964 | B5: IT | C5: 310000 | D5: 250000 | E5: =C5-D5 -> 60000
A6: 45965 | B6: Operations | C6: 220000 | D6: 145000 | E6: =C6-D6 -> 75000
A7: 45966 | B7: HR | C7: 110000 | D7: 85000 | E7: =C7-D7 -> 25000
A8: 45967 | B8: Sales | C8: 270000 | D8: 175000 | E8: =C8-D8 -> 95000
A9: 45968 | B9: IT | C9: 325000 | D9: 255000 | E9: =C9-D9 -> 70000
A10: 45969 | B10: Marketing | C10: 180000 | D10: 120000 | E10: =C10-D10 -> 60000
A11: 45970 | B11: Operations | C11: 240000 | D11: 160000 | E11: =C11-D11 -> 80000
A12: 45971 | B12: HR | C12: 125000 | D12: 90000 | E12: =C12-D12 -> 35000
A13: 45972 | B13: IT | C13: 300000 | D13: 210000 | E13: =C13-D13 -> 90000
A14: 45973 | B14: Sales | C14: 260000 | D14: 180000 | E14: =C14-D14 -> 80000
... A17: 45976 | B17: IT | C17: 340000 | D17: 260000 | E17: =C17-D17 -> 80000
A18: Total Profit | C18: =SUM(C3:C17) -> 3455000 | D18: =SUM(D3:D17) -> 2435000 | E18: =SUM(E3:E17) -> 1020000

Sheet Sheet2
A1: Department | B1: Total Revenue | C1: Total Expense | D1: Total Profit(Total Revenue - Total Expenses) | F1: Percentage | G1: Profit | H1: Revenue | I1: Expense
A2: Sales | B2: =SUMIF(Sheet1!B3:B17,"Sales",Sheet1!C3:C17) -> 770000 | C2: =SUMIF(Sheet1!B3:B17,"Sales",Sheet1!D3:D17) -> 515000 | D2: =B2-C2 -> 255000 | F2: IT | G2: =SUMIF(A$2:A$6,"IT",D$2:D$6)/D$7 -> 0.29411765 | H2: =SUMIF(A$2:A$6,"IT",B$2:B$6)/B$7 -> 0.36903039 | I2: =SUMIF(A$2:A$6,"IT",C$2:C$6)/C$7 -> 0.40041068
A3: Marketing | B3: =SUMIF(Sheet1!B4:B18,"Marketing",Sheet1!C4:C18) -> 505000 | C3: =SUMIF(Sheet1!B4:B18,"Marketing",Sheet1!D4:D18) -> 335000 | D3: =B3-C3 -> 170000 | F3: Sales | G3: =SUMIF(A$2:A$6,"Sales",D$2:D$6)/D$7 -> 0.25 | H3: =SUMIF(A$2:A$6,"Sales",B$2:B$6)/B$7 -> 0.22286541 | I3: =SUMIF(A$2:A$6,"Sales",C$2:C$6)/C$7 -> 0.21149897
A4: IT | B4: =SUMIF(Sheet1!B5:B19,"IT",Sheet1!C5:C19) -> 1275000 | C4: =SUMIF(Sheet1!B5:B19,"IT",Sheet1!D5:D19) -> 975000 | D4: =B4-C4 -> 300000 | F4: Marketing | G4: =SUMIF(A$2:A$6,"Marketing",D$2:D$6)/D$7 -> 0.16666667 | H4: =SUMIF(A$2:A$6,"Marketing",B$2:B$6)/B$7 -> 0.14616498 | I4: =SUMIF(A$2:A$6,"Marketing",C$2:C$6)/C$7 -> 0.137577
A5: Operations | B5: =SUMIF(Sheet1!B6:B20,"Operations",Sheet1!C6:C20) -> 670000 | C5: =SUMIF(Sheet1!B6:B20,"Operations",Sheet1!D6:D20) -> 435000 | D5: =B5-C5 -> 235000 | F5: HR | G5: =SUMIF(A$2:A$6,"HR",D$2:D$6)/D$7 -> 0.058823529 | H5: =SUMIF(A$2:A$6,"HR",B$2:B$6)/B$7 -> 0.068017366 | I5: =SUMIF(A$2:A$6,"HR",C$2:C$6)/C$7 -> 0.071868583
A6: HR | B6: =SUMIF(Sheet1!B7:B21,"HR",Sheet1!C7:C21) -> 235000 | C6: =SUMIF(Sheet1!B7:B21,"HR",Sheet1!D7:D21) -> 175000 | D6: =B6-C6 -> 60000 | F6: Operations | G6: =SUMIF(A$2:A$6,"Operations",D$2:D$6)/D$7 -> 0.23039216 | H6: =SUMIF(A$2:A$6,"Operations",B$2:B$6)/B$7 -> 0.19392185 | I6: =SUMIF(A$2:A$6,"Operations",C$2:C$6)/C$7 -> 0.17864476
A7: Grand Total | B7: =SUM(B2:B6) -> 3455000 | C7: =SUM(C2:C6) -> 2435000 | D7: =SUM(D2:D6) -> 1020000
