Workbook

Sheet Raw Data
A1: Date | B1: Department | C1: Revenue (Rs.) | D1: Expenses (Rs.) | E1: Profit (Rs.)
A2: 45962 | B2: Sales | C2: 240000 | D2: 160000 | E2: =C2-D2 -> 80000
A3: 45963 | B3: Marketing | C3: 150000 | D3: 105000 | E3: =C3-D3 -> 45000
A4: 45964 | B4: IT | C4: 310000 | D4: 250000 | E4: =C4-D4 -> 60000
A5: 45965 | B5: Operations | C5: 220000 | D5: 145000 | E5: =C5-D5 -> 75000
A6: 45966 | B6: HR | C6: 110000 | D6: 85000 | E6: =C6-D6 -> 25000
A7: 45967 | B7: Sales | C7: 270000 | D7: 175000 | E7: =C7-D7 -> 95000
A8: 45968 | B8: IT | C8: 325000 | D8: 255000 | E8: =C8-D8 -> 70000
A9: 45969 | B9: Marketing | C9: 180000 | D9: 120000 | E9: =C9-D9 -> 60000
A10: 45970 | B10: Operations | C10: 240000 | D10: 160000 | E10: =C10-D10 -> 80000
A11: 45971 | B11: HR | C11: 125000 | D11: 90000 | E11: =C11-D11 -> 35000
A12: 45972 | B12: IT | C12: 300000 | D12: 210000 | E12: =C12-D12 -> 90000
A13: 45973 | B13: Sales | C13: 260000 | D13: 180000 | E13: =C13-D13 -> 80000
... A16: 45976 | B16: IT | C16: 340000 | D16: 260000 | E16: =C16-D16 -> 80000

Sheet Summary
A1: Department | B1: Total Revenue | C1: Total Expense | D1: Total Profit
A2: Sales | B2: =SUMIF('Raw Data'!B2:B16,"Sales",'Raw Data'!C2:C16) -> 770000 | C2: =SUMIF('Raw Data'!B2:B16,"Sales",'Raw Data'!D2:D16) -> 515000 | D2: =B2-C2 -> 255000
A3: Marketing | B3: =SUMIF('Raw Data'!B3:B16,"Marketing",'Raw Data'!C3:C16) -> 505000 | C3: =SUMIF('Raw Data'!B3:B16,"Marketing",'Raw Data'!D3:D16) -> 335000 | D3: =B3-C3 -> 170000
A4: IT | B4: =SUMIF('Raw Data'!B4:B17,"IT",'Raw Data'!C4:C17) -> 1275000 | C4: =SUMIF('Raw Data'!B4:B17,"IT",'Raw Data'!D4:D17) -> 975000 | D4: =B4-C4 -> 300000
A5: Operations | B5: =SUMIF('Raw Data'!B5:B18,"Operations",'Raw Data'!C5:C18) -> 670000 | C5: =SUMIF('Raw Data'!B5:B18,"Operations",'Raw Data'!D5:D18) -> 435000 | D5: =B5-C5 -> 235000
A6: HR | B6: =SUMIF('Raw Data'!B6:B19,"HR",'Raw Data'!C6:C19) -> 235000 | C6: =SUMIF('Raw Data'!B6:B19,"HR",'Raw Data'!D6:D19) -> 175000 | D6: =B6-C6 -> 60000
A7: Grand Total | B7: =SUM(B2:B6) -> 3455000 | C7: =SUM(C2:C6) -> 2435000 | D7: =SUM(D2:D6) -> 1020000

Sheet charts and insights
